opentelemetry/instrumentation/elasticsearch/__init__.py
opentelemetry/instrumentation/elasticsearch/package.py
opentelemetry/instrumentation/elasticsearch/utils.py
opentelemetry/instrumentation/elasticsearch/version.py
opentelemetry_instrumentation_elasticsearch_fixed_sanitizer-0.49b2.dist-info/METADATA
opentelemetry_instrumentation_elasticsearch_fixed_sanitizer-0.49b2.dist-info/WHEEL
opentelemetry_instrumentation_elasticsearch_fixed_sanitizer-0.49b2.dist-info/entry_points.txt
opentelemetry_instrumentation_elasticsearch_fixed_sanitizer-0.49b2.dist-info/licenses/LICENSE
opentelemetry_instrumentation_elasticsearch_fixed_sanitizer-0.49b2.dist-info/RECORD
