Metadata-Version: 2.3
Name: opentelemetry-instrumentation-elasticsearch-fixed-sanitizer
Version: 0.49b2
Summary: OpenTelemetry elasticsearch instrumentation
Project-URL: Homepage, https://github.com/open-telemetry/opentelemetry-python-contrib/tree/main/instrumentation/opentelemetry-instrumentation-elasticsearch
Author-email: OpenTelemetry Authors <cncf-opentelemetry-contributors@lists.cncf.io>
License: Apache-2.0
Classifier: Development Status :: 4 - Beta
Classifier: Intended Audience :: Developers
Classifier: License :: OSI Approved :: Apache Software License
Classifier: Programming Language :: Python
Classifier: Programming Language :: Python :: 3
Classifier: Programming Language :: Python :: 3.8
Classifier: Programming Language :: Python :: 3.9
Classifier: Programming Language :: Python :: 3.10
Classifier: Programming Language :: Python :: 3.11
Classifier: Programming Language :: Python :: 3.12
Requires-Python: >=3.8
Requires-Dist: opentelemetry-api~=1.12
Requires-Dist: opentelemetry-instrumentation==0.49b2
Requires-Dist: opentelemetry-semantic-conventions==0.49b2
Requires-Dist: wrapt<2.0.0,>=1.0.0
Provides-Extra: instruments
Requires-Dist: elasticsearch>=6.0; extra == 'instruments'
